{
    "video_replies": [
      {
        "id": "r_3114",
        "kind": "VIDEO_REPLY",
        "uts": 1572597076,
        "payload": {
          "reply_detail_id": "3114",
          "user_id": "1934"
        }
      },
      {
        "id": "r_3113",
        "kind": "VIDEO_REPLY",
        "uts": 1572596985,
        "payload": {
          "reply_detail_id": "3113",
          "user_id": "1934"
        }
      },
      {
        "id": "r_3111",
        "kind": "VIDEO_REPLY",
        "uts": 1572596839,
        "payload": {
          "reply_detail_id": "3111",
          "user_id": "1934"
        }
      },
      {
        "id": "r_3106",
        "kind": "VIDEO_REPLY",
        "uts": 1572596347,
        "payload": {
          "reply_detail_id": "3106",
          "user_id": "1934"
        }
      },
      {
        "id": "r_3105",
        "kind": "VIDEO_REPLY",
        "uts": 1572595643,
        "payload": {
          "reply_detail_id": "3105",
          "user_id": "1934"
        }
      },
      {
        "id": "r_3100",
        "kind": "VIDEO_REPLY",
        "uts": 1572594026,
        "payload": {
          "reply_detail_id": "3100",
          "user_id": "1934"
        }
      },
      {
        "id": "r_3099",
        "kind": "VIDEO_REPLY",
        "uts": 1573050169,
        "payload": {
          "reply_detail_id": "3099",
          "user_id": "1934"
        }
      },
      {
        "id": "r_3098",
        "kind": "VIDEO_REPLY",
        "uts": 1573050140,
        "payload": {
          "reply_detail_id": "3098",
          "user_id": "1934"
        }
      },
      {
        "id": "r_3097",
        "kind": "VIDEO_REPLY",
        "uts": 1572593737,
        "payload": {
          "reply_detail_id": "3097",
          "user_id": "1934"
        }
      },
      {
        "id": "r_3096",
        "kind": "VIDEO_REPLY",
        "uts": 1572593642,
        "payload": {
          "reply_detail_id": "3096",
          "user_id": "1934"
        }
      },
      {
        "id": "r_3095",
        "kind": "VIDEO_REPLY",
        "uts": 1572593363,
        "payload": {
          "reply_detail_id": "3095",
          "user_id": "1934"
        }
      },
      {
        "id": "r_3094",
        "kind": "VIDEO_REPLY",
        "uts": 1572593283,
        "payload": {
          "reply_detail_id": "3094",
          "user_id": "1934"
        }
      }
    ],
    "users": {
      "1934": {
        "id": 1934,
        "user_name": "pepo_k2fs4mtu1z",
        "name": "Yogesh Sawant",
        "status": "ACTIVE",
        "approved_creator": 1,
        "uts": 1572598043,
        "ost_user_id": "c0b10884-bf45-472e-aa30-ffebbe96437f",
        "ost_token_holder_address": "0x3db658de63c8a7c655ec460f2a04f560022ce71a",
        "ost_status": "ACTIVATED",
        "profile_image_id": "3673"
      }
    },
    "video_descriptions": {
      "1062": {
        "text": "google google google google google google google google google google google google google google google googl",
        "includes": {}
      },
      "1063": {
        "text": "https://www.eventbrite.co.uk/e/epicenter-podcast-meetup-at-sf-blockchain-week-tickets-75885913811",
        "includes": {
          "https://www.eventbrite.co.uk/e/epicenter-podcast-meetup-at-sf-blockchain-week-tickets-75885913811": {
            "kind": "links",
            "id": "366"
          }
        }
      },
      "1064": {
        "text": "Test description to be added into the video for test 1 2 3 4",
        "includes": {}
      },
      "1065": {
        "text": "Great Things Happen ",
        "includes": {}
      },
      "1066": {
        "text": "#video #video #video03 #video04 #videodelete www.google.com www.pepo.com",
        "includes": {
          "#video": {
            "kind": "tags",
            "id": 65
          },
          "#video03": {
            "kind": "tags",
            "id": 83
          },
          "#video04": {
            "kind": "tags",
            "id": 84
          },
          "#videodelete": {
            "kind": "tags",
            "id": 10211
          },
          "www.pepo.com": {
            "kind": "links",
            "id": "371"
          },
          "www.google.com": {
            "kind": "links",
            "id": "370"
          },
          "Www.google.com": {
            "kind": "links",
            "id": "82"
          }
        }
      },
      "1067": {
        "text": "Update description hi this is for test go back go back",
        "includes": {}
      },
      "1071": {
        "text": "#goto # test wow great feature will land on video page itself",
        "includes": {
          "#goto": {
            "kind": "tags",
            "id": 10245
          }
        }
      },
      "1072": {
        "text": "#Dandiya #&lt;&gt; #google  #drive #drop #€ #addsd1234 #1233ddff  #टेस्ट #पेपो ",
        "includes": {
          "#drop": {
            "kind": "tags",
            "id": 98
          },
          "#google": {
            "kind": "tags",
            "id": 88
          },
          "#1233ddff": {
            "kind": "tags",
            "id": 10249
          },
          "#addsd1234": {
            "kind": "tags",
            "id": 10248
          },
          "#dandiya": {
            "kind": "tags",
            "id": 10246
          },
          "#drive": {
            "kind": "tags",
            "id": 10247
          }
        }
      },
      "1077": {
        "text": " #tagwalavideo #test ",
        "includes": {
          "#tagwalavideo": {
            "kind": "tags",
            "id": 117
          },
          "#test": {
            "kind": "tags",
            "id": 52
          }
        }
      },
      "1079": {
        "text": "#frog",
        "includes": {
          "#frog": {
            "kind": "tags",
            "id": 10250
          }
        }
      },
      "1080": {
        "text": "Test Description what the testing #google ",
        "includes": {
          "#google": {
            "kind": "tags",
            "id": 88
          }
        }
      }
    },
    "tags": {
      "52": {
        "id": 52,
        "text": "test",
        "weight": "7",
        "video_weight": "77",
        "status": "ACTIVE",
        "uts": 1573458335
      },
      "65": {
        "id": 65,
        "text": "video",
        "weight": "0",
        "video_weight": "7",
        "status": "ACTIVE",
        "uts": 1572593867
      },
      "83": {
        "id": 83,
        "text": "video03",
        "weight": "0",
        "video_weight": "4",
        "status": "ACTIVE",
        "uts": 1572593867
      },
      "84": {
        "id": 84,
        "text": "video04",
        "weight": "0",
        "video_weight": "3",
        "status": "ACTIVE",
        "uts": 1572593867
      },
      "88": {
        "id": 88,
        "text": "google",
        "weight": "0",
        "video_weight": "4",
        "status": "ACTIVE",
        "uts": 1572958953
      },
      "98": {
        "id": 98,
        "text": "drop",
        "weight": "0",
        "video_weight": "2",
        "status": "ACTIVE",
        "uts": 1572596347
      },
      "117": {
        "id": 117,
        "text": "tagwalavideo",
        "weight": "0",
        "video_weight": "57",
        "status": "ACTIVE",
        "uts": 1573202336
      },
      "10211": {
        "id": 10211,
        "text": "videodelete",
        "weight": "0",
        "video_weight": "2",
        "status": "ACTIVE",
        "uts": 1572593867
      },
      "10245": {
        "id": 10245,
        "text": "goto",
        "weight": "0",
        "video_weight": "1",
        "status": "ACTIVE",
        "uts": 1572595643
      },
      "10246": {
        "id": 10246,
        "text": "dandiya",
        "weight": "0",
        "video_weight": "1",
        "status": "ACTIVE",
        "uts": 1572596347
      },
      "10247": {
        "id": 10247,
        "text": "drive",
        "weight": "0",
        "video_weight": "1",
        "status": "ACTIVE",
        "uts": 1572596347
      },
      "10248": {
        "id": 10248,
        "text": "addsd1234",
        "weight": "0",
        "video_weight": "1",
        "status": "ACTIVE",
        "uts": 1572596347
      },
      "10249": {
        "id": 10249,
        "text": "1233ddff",
        "weight": "0",
        "video_weight": "1",
        "status": "ACTIVE",
        "uts": 1572596347
      },
      "10250": {
        "id": 10250,
        "text": "frog",
        "weight": "0",
        "video_weight": "1",
        "status": "ACTIVE",
        "uts": 1572596985
      }
    },
    "links": {
      "44": {
        "id": 44,
        "url": "http://www.pepo.com",
        "kind": "SOCIAL_LINK",
        "uts": 1565695575
      },
      "80": {
        "id": 80,
        "url": "http://www.google.com",
        "kind": "SOCIAL_LINK",
        "uts": 1566472677
      },
      "81": {
        "id": 81,
        "url": "http://www.google.com",
        "kind": "SOCIAL_LINK",
        "uts": 1566482648
      },
      "82": {
        "id": 82,
        "url": "http://Www.google.com",
        "kind": "SOCIAL_LINK",
        "uts": 1566814218
      },
      "267": {
        "id": 267,
        "url": "http://www.pepo.com",
        "kind": "SOCIAL_LINK",
        "uts": 1569605095
      },
      "289": {
        "id": 289,
        "url": "http://www.google.com",
        "kind": "SOCIAL_LINK",
        "uts": 1571666978
      },
      "302": {
        "id": 302,
        "url": "http://www.pepo.com",
        "kind": "SOCIAL_LINK",
        "uts": 1571834737
      },
      "328": {
        "id": 328,
        "url": "https://www.eventbrite.co.uk/e/epicenter-podcast-meetup-at-sf-blockchain-week-tickets-75885913811",
        "kind": "SOCIAL_LINK",
        "uts": 1572431209
      },
      "329": {
        "id": 329,
        "url": "https://www.eventbrite.co.uk/e/epicenter-podcast-meetup-at-sf-blockchain-week-tickets-75885913811",
        "kind": "SOCIAL_LINK",
        "uts": 1572431429
      },
      "345": {
        "id": 345,
        "url": "https://www.eventbrite.co.uk/e/epicenter-podcast-meetup-at-sf-blockchain-week-tickets-75885913811",
        "kind": "SOCIAL_LINK",
        "uts": 1572443812
      },
      "355": {
        "id": 355,
        "url": "https://www.eventbrite.co.uk/e/epicenter-podcast-meetup-at-sf-blockchain-week-tickets-75885913811",
        "kind": "SOCIAL_LINK",
        "uts": 1572445402
      },
      "360": {
        "id": 360,
        "url": "http://www.google.com",
        "kind": "SOCIAL_LINK",
        "uts": 1572521587
      },
      "364": {
        "id": 364,
        "url": "https://www.eventbrite.co.uk/e/epicenter-podcast-meetup-at-sf-blockchain-week-tickets-75885913811",
        "kind": "SOCIAL_LINK",
        "uts": 1572593283
      },
      "365": {
        "id": 365,
        "url": "https://www.eventbrite.co.uk/e/epicenter-podcast-meetup-at-sf-blockchain-week-tickets-75885913811",
        "kind": "SOCIAL_LINK",
        "uts": 1572593363
      },
      "366": {
        "id": 366,
        "url": "https://www.eventbrite.co.uk/e/epicenter-podcast-meetup-at-sf-blockchain-week-tickets-75885913811",
        "kind": "SOCIAL_LINK",
        "uts": 1572593363
      },
      "367": {
        "id": 367,
        "url": "http://text.com",
        "kind": "SOCIAL_LINK",
        "uts": 1572593642
      },
      "368": {
        "id": 368,
        "url": "http://google.com",
        "kind": "SOCIAL_LINK",
        "uts": 1572593737
      },
      "369": {
        "id": 369,
        "url": "http://www.whatsapp.com",
        "kind": "SOCIAL_LINK",
        "uts": 1572593867
      },
      "370": {
        "id": 370,
        "url": "http://www.google.com",
        "kind": "SOCIAL_LINK",
        "uts": 1572593867
      },
      "371": {
        "id": 371,
        "url": "http://www.pepo.com",
        "kind": "SOCIAL_LINK",
        "uts": 1572593867
      },
      "375": {
        "id": 375,
        "url": "http://google.com",
        "kind": "SOCIAL_LINK",
        "uts": 1572595643
      }
    },
    "images": {
      "3673": {
        "id": 3673,
        "resolutions": {
          "144w": {
            "size": 5511,
            "height": "144",
            "width": "144",
            "url": "https://dbvoeb7t6hffk.cloudfront.net/pepo-staging1000/ua/images/1934-db6e2d5ab26f9640cf758ebddbc0970d-144w.jpg"
          },
          "original": {
            "url": "https://pbs.twimg.com/profile_images/1176128580830392320/jTi0PtIH.jpg"
          }
        },
        "status": "ACTIVE",
        "uts": 1572591106
      },
      "3675": {
        "id": 3675,
        "resolutions": {
          "288w": {
            "size": 11765,
            "height": "512",
            "width": "288",
            "url": "https://dbvoeb7t6hffk.cloudfront.net/pepo-staging1000/ua/images/1934-06f8d3fed1b5bbf9550bd18e70c9c17f-288w.jpg"
          },
          "original": {
            "size": 18342,
            "height": 1280,
            "width": 720,
            "url": "https://dbvoeb7t6hffk.cloudfront.net/pepo-staging1000/ua/images/1934-06f8d3fed1b5bbf9550bd18e70c9c17f-original.jpg"
          }
        },
        "status": "ACTIVE",
        "uts": 1572593293
      },
      "3676": {
        "id": 3676,
        "resolutions": {
          "288w": {
            "size": 18563,
            "height": "512",
            "width": "288",
            "url": "https://dbvoeb7t6hffk.cloudfront.net/pepo-staging1000/ua/images/1934-356157a3707802599836f9d9c65ef663-288w.jpg"
          },
          "original": {
            "size": 32202,
            "height": 1280,
            "width": 720,
            "url": "https://dbvoeb7t6hffk.cloudfront.net/pepo-staging1000/ua/images/1934-356157a3707802599836f9d9c65ef663-original.jpg"
          }
        },
        "status": "ACTIVE",
        "uts": 1572593373
      },
      "3677": {
        "id": 3677,
        "resolutions": {
          "288w": {
            "size": 18490,
            "height": "512",
            "width": "288",
            "url": "https://dbvoeb7t6hffk.cloudfront.net/pepo-staging1000/ua/images/1934-bd3d411c50545ed615b155341662a6b6-288w.jpg"
          },
          "original": {
            "size": 30934,
            "height": 1280,
            "width": 720,
            "url": "https://dbvoeb7t6hffk.cloudfront.net/pepo-staging1000/ua/images/1934-bd3d411c50545ed615b155341662a6b6-original.jpg"
          }
        },
        "status": "ACTIVE",
        "uts": 1572593652
      },
      "3678": {
        "id": 3678,
        "resolutions": {
          "288w": {
            "size": 10122,
            "height": "512",
            "width": "288",
            "url": "https://dbvoeb7t6hffk.cloudfront.net/pepo-staging1000/ua/images/1934-bb712efb8ebe3dc9dba41ed1ac3775c7-288w.jpg"
          },
          "original": {
            "size": 16974,
            "height": 1280,
            "width": 720,
            "url": "https://dbvoeb7t6hffk.cloudfront.net/pepo-staging1000/ua/images/1934-bb712efb8ebe3dc9dba41ed1ac3775c7-original.jpg"
          }
        },
        "status": "ACTIVE",
        "uts": 1572593747
      },
      "3679": {
        "id": 3679,
        "resolutions": {
          "288w": {
            "size": 12477,
            "height": "512",
            "width": "288",
            "url": "https://dbvoeb7t6hffk.cloudfront.net/pepo-staging1000/ua/images/1934-279256bcde3297604d065444b8142bbf-288w.jpg"
          },
          "original": {
            "size": 20144,
            "height": 1280,
            "width": 720,
            "url": "https://dbvoeb7t6hffk.cloudfront.net/pepo-staging1000/ua/images/1934-279256bcde3297604d065444b8142bbf-original.jpg"
          }
        },
        "status": "ACTIVE",
        "uts": 1572593877
      },
      "3680": {
        "id": 3680,
        "resolutions": {
          "288w": {
            "size": 12869,
            "height": "512",
            "width": "288",
            "url": "https://dbvoeb7t6hffk.cloudfront.net/pepo-staging1000/ua/images/1934-d1c7ebf8471f952cff0f67aedcd12813-288w.jpg"
          },
          "original": {
            "size": 20021,
            "height": 1280,
            "width": 720,
            "url": "https://dbvoeb7t6hffk.cloudfront.net/pepo-staging1000/ua/images/1934-d1c7ebf8471f952cff0f67aedcd12813-original.jpg"
          }
        },
        "status": "ACTIVE",
        "uts": 1572593960
      },
      "3681": {
        "id": 3681,
        "resolutions": {
          "288w": {
            "size": 9958,
            "height": "512",
            "width": "288",
            "url": "https://dbvoeb7t6hffk.cloudfront.net/pepo-staging1000/ua/images/1934-e650cff65430023d3f5b36279bfd1028-288w.jpg"
          },
          "original": {
            "size": 16862,
            "height": 1280,
            "width": 720,
            "url": "https://dbvoeb7t6hffk.cloudfront.net/pepo-staging1000/ua/images/1934-e650cff65430023d3f5b36279bfd1028-original.jpg"
          }
        },
        "status": "ACTIVE",
        "uts": 1572594037
      },
      "3686": {
        "id": 3686,
        "resolutions": {
          "288w": {
            "size": 11637,
            "height": "512",
            "width": "288",
            "url": "https://dbvoeb7t6hffk.cloudfront.net/pepo-staging1000/ua/images/1934-8219097045530acd57f9715728dbbe02-288w.jpg"
          },
          "original": {
            "size": 18604,
            "height": 1280,
            "width": 720,
            "url": "https://dbvoeb7t6hffk.cloudfront.net/pepo-staging1000/ua/images/1934-8219097045530acd57f9715728dbbe02-original.jpg"
          }
        },
        "status": "ACTIVE",
        "uts": 1572595653
      },
      "3687": {
        "id": 3687,
        "resolutions": {
          "288w": {
            "size": 12277,
            "height": "512",
            "width": "288",
            "url": "https://dbvoeb7t6hffk.cloudfront.net/pepo-staging1000/ua/images/1934-51e37f689332b326fdba973f5fe56827-288w.jpg"
          },
          "original": {
            "size": 20351,
            "height": 1280,
            "width": 720,
            "url": "https://dbvoeb7t6hffk.cloudfront.net/pepo-staging1000/ua/images/1934-51e37f689332b326fdba973f5fe56827-original.jpg"
          }
        },
        "status": "ACTIVE",
        "uts": 1572596357
      },
      "3692": {
        "id": 3692,
        "resolutions": {
          "288w": {
            "size": 18101,
            "height": "512",
            "width": "288",
            "url": "https://dbvoeb7t6hffk.cloudfront.net/pepo-staging1000/ua/images/1934-edd3d687418c63ce7a651f2619aa3786-288w.jpg"
          },
          "original": {
            "size": 33238,
            "height": 1280,
            "width": 720,
            "url": "https://dbvoeb7t6hffk.cloudfront.net/pepo-staging1000/ua/images/1934-edd3d687418c63ce7a651f2619aa3786-original.jpg"
          }
        },
        "status": "ACTIVE",
        "uts": 1572596850
      },
      "3694": {
        "id": 3694,
        "resolutions": {
          "288w": {
            "size": 16730,
            "height": "512",
            "width": "288",
            "url": "https://dbvoeb7t6hffk.cloudfront.net/pepo-staging1000/ua/images/1934-a1a726c313151e0a16520bfbee10a53d-288w.jpg"
          },
          "original": {
            "size": 34049,
            "height": 1280,
            "width": 720,
            "url": "https://dbvoeb7t6hffk.cloudfront.net/pepo-staging1000/ua/images/1934-a1a726c313151e0a16520bfbee10a53d-original.jpg"
          }
        },
        "status": "ACTIVE",
        "uts": 1572596995
      },
      "3695": {
        "id": 3695,
        "resolutions": {
          "288w": {
            "size": 13225,
            "height": "512",
            "width": "288",
            "url": "https://dbvoeb7t6hffk.cloudfront.net/pepo-staging1000/ua/images/1934-09ba585ee830101a49668aa41ca552dc-288w.jpg"
          },
          "original": {
            "size": 22716,
            "height": 1280,
            "width": 720,
            "url": "https://dbvoeb7t6hffk.cloudfront.net/pepo-staging1000/ua/images/1934-09ba585ee830101a49668aa41ca552dc-original.jpg"
          }
        },
        "status": "ACTIVE",
        "uts": 1572597086
      }
    },
    "videos": {
      "3094": {
        "id": 3094,
        "resolutions": {
          "576w": {
            "size": 380002,
            "height": "1024",
            "width": "576",
            "url": "https://dbvoeb7t6hffk.cloudfront.net/pepo-staging1000/ua/videos/1934-beaaac8c711b52b6d8337fbd183cbc6e-576w.mp4"
          },
          "original": {
            "size": 716164,
            "height": 1280,
            "width": 720,
            "url": "https://dbvoeb7t6hffk.cloudfront.net/pepo-staging1000/ua/videos/1934-beaaac8c711b52b6d8337fbd183cbc6e-original.mp4"
          }
        },
        "status": "ACTIVE",
        "kind": "POST",
        "poster_image_id": "3675",
        "uts": 1572593314
      },
      "3095": {
        "id": 3095,
        "resolutions": {
          "576w": {
            "size": 188463,
            "height": "1024",
            "width": "576",
            "url": "https://dbvoeb7t6hffk.cloudfront.net/pepo-staging1000/ua/videos/1934-56aa8256017aaadb97f5842d494bcfb9-576w.mp4"
          },
          "original": {
            "size": 393391,
            "height": 1280,
            "width": 720,
            "url": "https://dbvoeb7t6hffk.cloudfront.net/pepo-staging1000/ua/videos/1934-56aa8256017aaadb97f5842d494bcfb9-original.mp4"
          }
        },
        "status": "ACTIVE",
        "kind": "POST",
        "poster_image_id": "3676",
        "uts": 1572593393
      },
      "3096": {
        "id": 3096,
        "resolutions": {
          "576w": {
            "size": 440859,
            "height": "1024",
            "width": "576",
            "url": "https://dbvoeb7t6hffk.cloudfront.net/pepo-staging1000/ua/videos/1934-867a0c81467ae8b7fa32b8de509eeb46-576w.mp4"
          },
          "original": {
            "size": 930534,
            "height": 1280,
            "width": 720,
            "url": "https://dbvoeb7t6hffk.cloudfront.net/pepo-staging1000/ua/videos/1934-867a0c81467ae8b7fa32b8de509eeb46-original.mp4"
          }
        },
        "status": "ACTIVE",
        "kind": "POST",
        "poster_image_id": "3677",
        "uts": 1572593672
      },
      "3097": {
        "id": 3097,
        "resolutions": {
          "576w": {
            "size": 426036,
            "height": "1024",
            "width": "576",
            "url": "https://dbvoeb7t6hffk.cloudfront.net/pepo-staging1000/ua/videos/1934-0bb684a9d7a9d1bebdce46a776b62d15-576w.mp4"
          },
          "original": {
            "size": 986142,
            "height": 1280,
            "width": 720,
            "url": "https://dbvoeb7t6hffk.cloudfront.net/pepo-staging1000/ua/videos/1934-0bb684a9d7a9d1bebdce46a776b62d15-original.mp4"
          }
        },
        "status": "ACTIVE",
        "kind": "POST",
        "poster_image_id": "3678",
        "uts": 1572593767
      },
      "3098": {
        "id": 3098,
        "resolutions": {
          "576w": {
            "size": 278341,
            "height": "1024",
            "width": "576",
            "url": "https://dbvoeb7t6hffk.cloudfront.net/pepo-staging1000/ua/videos/1934-4a13b568e8eb8ee84d7f1836e19f0e5e-576w.mp4"
          },
          "original": {
            "size": 624002,
            "height": 1280,
            "width": 720,
            "url": "https://dbvoeb7t6hffk.cloudfront.net/pepo-staging1000/ua/videos/1934-4a13b568e8eb8ee84d7f1836e19f0e5e-original.mp4"
          }
        },
        "status": "ACTIVE",
        "kind": "POST",
        "poster_image_id": "3679",
        "uts": 1572593897
      },
      "3099": {
        "id": 3099,
        "resolutions": {
          "576w": {
            "size": 273903,
            "height": "1024",
            "width": "576",
            "url": "https://dbvoeb7t6hffk.cloudfront.net/pepo-staging1000/ua/videos/1934-fa48fa18ce3df1ccbdaaa037d830b2fe-576w.mp4"
          },
          "original": {
            "size": 544827,
            "height": 1280,
            "width": 720,
            "url": "https://dbvoeb7t6hffk.cloudfront.net/pepo-staging1000/ua/videos/1934-fa48fa18ce3df1ccbdaaa037d830b2fe-original.mp4"
          }
        },
        "status": "ACTIVE",
        "kind": "POST",
        "poster_image_id": "3680",
        "uts": 1572593980
      },
      "3100": {
        "id": 3100,
        "resolutions": {
          "576w": {
            "size": 463086,
            "height": "1024",
            "width": "576",
            "url": "https://dbvoeb7t6hffk.cloudfront.net/pepo-staging1000/ua/videos/1934-618982762f98e5140cdc6a5aceab4ddd-576w.mp4"
          },
          "original": {
            "size": 1134072,
            "height": 1280,
            "width": 720,
            "url": "https://dbvoeb7t6hffk.cloudfront.net/pepo-staging1000/ua/videos/1934-618982762f98e5140cdc6a5aceab4ddd-original.mp4"
          }
        },
        "status": "ACTIVE",
        "kind": "POST",
        "poster_image_id": "3681",
        "uts": 1572594057
      },
      "3105": {
        "id": 3105,
        "resolutions": {
          "576w": {
            "size": 675674,
            "height": "1024",
            "width": "576",
            "url": "https://dbvoeb7t6hffk.cloudfront.net/pepo-staging1000/ua/videos/1934-600db556de14af8bc2dbf6015462e098-576w.mp4"
          },
          "original": {
            "size": 1552303,
            "height": 1280,
            "width": 720,
            "url": "https://dbvoeb7t6hffk.cloudfront.net/pepo-staging1000/ua/videos/1934-600db556de14af8bc2dbf6015462e098-original.mp4"
          }
        },
        "status": "ACTIVE",
        "kind": "POST",
        "poster_image_id": "3686",
        "uts": 1572595703
      },
      "3106": {
        "id": 3106,
        "resolutions": {
          "576w": {
            "size": 389065,
            "height": "1024",
            "width": "576",
            "url": "https://dbvoeb7t6hffk.cloudfront.net/pepo-staging1000/ua/videos/1934-380ee7db78f9d6ec5bbd554ca3bd51d6-576w.mp4"
          },
          "original": {
            "size": 1039039,
            "height": 1280,
            "width": 720,
            "url": "https://dbvoeb7t6hffk.cloudfront.net/pepo-staging1000/ua/videos/1934-380ee7db78f9d6ec5bbd554ca3bd51d6-original.mp4"
          }
        },
        "status": "ACTIVE",
        "kind": "POST",
        "poster_image_id": "3687",
        "uts": 1572596378
      },
      "3111": {
        "id": 3111,
        "resolutions": {
          "576w": {
            "size": 387499,
            "height": "1024",
            "width": "576",
            "url": "https://dbvoeb7t6hffk.cloudfront.net/pepo-staging1000/ua/videos/1934-3dab9b0ed7d968b811e49ff2aefa8f6f-576w.mp4"
          },
          "original": {
            "size": 898100,
            "height": 1280,
            "width": 720,
            "url": "https://dbvoeb7t6hffk.cloudfront.net/pepo-staging1000/ua/videos/1934-3dab9b0ed7d968b811e49ff2aefa8f6f-original.mp4"
          }
        },
        "status": "ACTIVE",
        "kind": "POST",
        "poster_image_id": "3692",
        "uts": 1572596870
      },
      "3113": {
        "id": 3113,
        "resolutions": {
          "576w": {
            "size": 209066,
            "height": "1024",
            "width": "576",
            "url": "https://dbvoeb7t6hffk.cloudfront.net/pepo-staging1000/ua/videos/1934-a672eb55a982d1b915a721a308f46f0d-576w.mp4"
          },
          "original": {
            "size": 460972,
            "height": 1280,
            "width": 720,
            "url": "https://dbvoeb7t6hffk.cloudfront.net/pepo-staging1000/ua/videos/1934-a672eb55a982d1b915a721a308f46f0d-original.mp4"
          }
        },
        "status": "ACTIVE",
        "kind": "POST",
        "poster_image_id": "3694",
        "uts": 1572597015
      },
      "3114": {
        "id": 3114,
        "resolutions": {
          "576w": {
            "size": 568253,
            "height": "1024",
            "width": "576",
            "url": "https://dbvoeb7t6hffk.cloudfront.net/pepo-staging1000/ua/videos/1934-7eccd039fe3b1927b4e17c149e5d68b8-576w.mp4"
          },
          "original": {
            "size": 1393347,
            "height": 1280,
            "width": 720,
            "url": "https://dbvoeb7t6hffk.cloudfront.net/pepo-staging1000/ua/videos/1934-7eccd039fe3b1927b4e17c149e5d68b8-original.mp4"
          }
        },
        "status": "ACTIVE",
        "kind": "POST",
        "poster_image_id": "3695",
        "uts": 1572597106
      }
    },
    "reply_details": {
      "3094": {
        "id": 3095,
        "creator_user_id": 1934,
        "entity_kind": "VIDEO",
        "entity_id": "3094",
        "description_id": 1062,
        "link_ids": [
          364
        ],
        "total_contributed_by": 0,
        "total_amount_raised_in_wei": "0",
        "total_transactions": 0,
        "parent_id": 12,
        "parent_kind": "VIDEO",
        "uts": 1572593283
      },
      "3095": {
        "id": 3096,
        "creator_user_id": 1934,
        "entity_kind": "VIDEO",
        "entity_id": "3095",
        "description_id": 1063,
        "link_ids": [
          365
        ],
        "total_contributed_by": 0,
        "total_amount_raised_in_wei": "0",
        "total_transactions": 0,
        "parent_id": 12,
        "parent_kind": "VIDEO",
        "uts": 1572593363
      },
      "3096": {
        "id": 3097,
        "creator_user_id": 1934,
        "entity_kind": "VIDEO",
        "entity_id": "3096",
        "description_id": 1064,
        "link_ids": [
          367
        ],
        "total_contributed_by": 0,
        "total_amount_raised_in_wei": "0",
        "total_transactions": 0,
        "parent_id": 12,
        "parent_kind": "VIDEO",
        "uts": 1572593642
      },
      "3097": {
        "id": 3098,
        "creator_user_id": 1934,
        "entity_kind": "VIDEO",
        "entity_id": "3097",
        "description_id": 1065,
        "link_ids": [
          368
        ],
        "total_contributed_by": 0,
        "total_amount_raised_in_wei": "0",
        "total_transactions": 0,
        "parent_id": 12,
        "parent_kind": "VIDEO",
        "uts": 1572593737
      },
      "3098": {
        "id": 3099,
        "creator_user_id": 1934,
        "entity_kind": "VIDEO",
        "entity_id": "3098",
        "description_id": 1066,
        "link_ids": [
          369
        ],
        "total_contributed_by": 1,
        "total_amount_raised_in_wei": "1000000000000000000",
        "total_transactions": 1,
        "parent_id": 12,
        "parent_kind": "VIDEO",
        "uts": 1573050140
      },
      "3099": {
        "id": 3100,
        "creator_user_id": 1934,
        "entity_kind": "VIDEO",
        "entity_id": "3099",
        "description_id": 1067,
        "link_ids": null,
        "total_contributed_by": 1,
        "total_amount_raised_in_wei": "1000000000000000000",
        "total_transactions": 1,
        "parent_id": 12,
        "parent_kind": "VIDEO",
        "uts": 1573050169
      },
      "3100": {
        "id": 3101,
        "creator_user_id": 1934,
        "entity_kind": "VIDEO",
        "entity_id": "3100",
        "description_id": null,
        "link_ids": null,
        "total_contributed_by": 0,
        "total_amount_raised_in_wei": "0",
        "total_transactions": 0,
        "parent_id": 12,
        "parent_kind": "VIDEO",
        "uts": 1572594026
      },
      "3105": {
        "id": 3106,
        "creator_user_id": 1934,
        "entity_kind": "VIDEO",
        "entity_id": "3105",
        "description_id": 1071,
        "link_ids": [
          375
        ],
        "total_contributed_by": 0,
        "total_amount_raised_in_wei": "0",
        "total_transactions": 0,
        "parent_id": 12,
        "parent_kind": "VIDEO",
        "uts": 1572595643
      },
      "3106": {
        "id": 3107,
        "creator_user_id": 1934,
        "entity_kind": "VIDEO",
        "entity_id": "3106",
        "description_id": 1072,
        "link_ids": null,
        "total_contributed_by": 0,
        "total_amount_raised_in_wei": "0",
        "total_transactions": 0,
        "parent_id": 12,
        "parent_kind": "VIDEO",
        "uts": 1572596347
      },
      "3111": {
        "id": 3112,
        "creator_user_id": 1934,
        "entity_kind": "VIDEO",
        "entity_id": "3111",
        "description_id": 1077,
        "link_ids": null,
        "total_contributed_by": 0,
        "total_amount_raised_in_wei": "0",
        "total_transactions": 0,
        "parent_id": 12,
        "parent_kind": "VIDEO",
        "uts": 1572596839
      },
      "3113": {
        "id": 3114,
        "creator_user_id": 1934,
        "entity_kind": "VIDEO",
        "entity_id": "3113",
        "description_id": 1079,
        "link_ids": null,
        "total_contributed_by": 0,
        "total_amount_raised_in_wei": "0",
        "total_transactions": 0,
        "parent_id": 12,
        "parent_kind": "VIDEO",
        "uts": 1572596985
      },
      "3114": {
        "id": 3115,
        "creator_user_id": 1934,
        "entity_kind": "VIDEO",
        "entity_id": "3114",
        "description_id": 1080,
        "link_ids": null,
        "total_contributed_by": 0,
        "total_amount_raised_in_wei": "0",
        "total_transactions": 0,
        "parent_id": 12,
        "parent_kind": "VIDEO",
        "uts": 1572597076
      }
    },
    "price_points": {
      "OST": {
        "USD": "0.0109743920",
        "EUR": "0.0099515697",
        "GBP": "0.0085754158",
        "decimals": 18
      }
    },
    "token": {
      "id": 1,
      "name": "PEPO",
      "symbol": "PEPO",
      "decimal": 18,
      "aux_chain_id": 197,
      "ost_token_id": 1185,
      "conversion_factor": "1.000000",
      "company_token_holder_address": "0xf88bfc4c02e0827f68a8d9dbfedf5169025daa73",
      "utility_branded_token": "0xf3e67271386fe994eb994c713b52556a38bba094",
      "rule_addresses": "{\"Pricer\":\"0xc578002ee6c59ea4cdc31295ec15694b14f6dcbd\",\"Direct Transfer\":\"0xae7ac3b5e45f9bafe3e2578e94abeda6075649c5\"}",
      "ost_company_user_id": "0d91bb6f-7301-4bb8-8cf0-655e16de4f84",
      "created_at": 1560332210,
      "uts": 1568125863
    },
    "meta": {
      "next_page_payload": null
    },
    "result_type": "video_replies"
}